{"version":3,"file":"build/wavesurfer.min.js","sources":["src/wavesurfer.js","src/webaudio.js","src/webaudio.buffer.js","src/webaudio.media.js","src/audioelement.js","src/drawer.js","src/drawer.canvas.js"],"names":["WaveSurfer","defaultParams","height","waveColor","progressColor","cursorColor","selectionColor","selectionBorder","selectionForeground","selectionBorderColor","cursorWidth","markerWidth","skipLength","minPxPerSec","pixelRatio","window","devicePixelRatio","fillParent","scrollParent","normalize","audioContext","container","dragSelection","loopSelection","audioRate","interact","renderer","backend","init","params","this","util","extend","document","querySelector","Error","markers","once","bindMarks","bind","bindRegions","regions","savedVolume","isMuted","bindUserAction","createDrawer","createBackend","my","onUserAction","fireEvent","addEventListener","on","removeEventListener","createMedia","url","media","createElement","controls","autoplay","src","prevMedia","removeChild","appendChild","drawer","Object","create","Drawer","drawBuffer","progress","getPlayedPercents","setTimeout","seekTo","id","mark","remove","drag","dragging","updateSelection","clearSelection","e","destroy","restartAnimationLoop","message","requestFrame","requestAnimationFrame","webkitRequestAnimationFrame","frame","isPaused","getDuration","getCurrentTime","play","start","end","pause","playPause","playPauseSelection","sel","getSelection","startPercentage","skipBackward","seconds","skip","skipForward","offset","timings","seekAndCenter","recenter","paused","oldScrollParent","getVolume","setVolume","width","realPxPerSec","stop","newVolume","toggleMute","toggleScroll","options","opts","getId","percentage","position","update","Mark","type","updateSelectionByMark","moveMark","updateMark","removeMark","addMark","clearMarks","keys","forEach","redrawRegions","region","clearRegions","startPosition","endPercentage","endPosition","Region","updateRegion","removeRegion","addRegion","duration","Math","max","min","length","getWidth","round","drawPeaks","getPeaks","drawAsItPlays","peaks","frameTime","prevTime","drawFrame","time","Infinity","Uint8Array","index","waveform","setWidth","clearWave","drawWave","loadArrayBuffer","arraybuffer","decodeArrayBuffer","data","loadDecodedBuffer","buffer","empty","load","loadBlob","blob","reader","FileReader","onProgress","target","result","readAsArrayBuffer","loadBuffer","loadStream","loadAudioElement","downloadArrayBuffer","callback","ajax","responseType","statusText","lengthComputable","percentComplete","loaded","total","played","marker","firedIn","firedOut","un","disconnectSource","unAll","markDrag","selection","selMark0","selMark1","percent0","percent1","color","tmpPercent","draggable","toggleLoopSelection","startTime","getTitle","endTime","enableInteraction","disableInteraction","toggleInteraction","apply","slice","join","key","Observer","event","fn","handlers","push","i","splice","handler","args","Array","prototype","call","arguments","dest","sources","source","random","toString","substring","values","len","val","abs","xhr","XMLHttpRequest","fired100","open","method","status","response","send","throttle","func","wait","context","timeout","previous","later","leading","Date","now","remaining","clearTimeout","trailing","WebAudio","scriptBufferSize","fftSize","getAudioContext","AudioContext","webkitAudioContext","ac","loop","prevFrameTime","scheduledPause","firedFinish","postInit","createVolumeNode","createScriptNode","createAnalyserNode","setPlaybackRate","disconnectFilters","filters","filter","disconnect","setFilter","setFilters","reduce","prev","curr","connect","analyser","gainNode","bufferSize","scriptNode","createScriptProcessor","createJavaScriptNode","destination","onaudioprocess","onPlayFrame","loopStart","loopEnd","createAnalyser","analyserData","frequencyBinCount","createGain","createGainNode","newGain","gain","value","errback","decodeAudioData","sampleSize","sampleStep","channels","numberOfChannels","Float32Array","c","chan","getChannelData","j","startPercent","endPercent","getByteTimeDomainData","playbackRate","WebAudioBuffer","lastStartPosition","lastPlay","lastPause","nextPause","currentTime","createSource","createBufferSource","noteGrainOn","noteOff","WebAudioMedia","maxCurrentTime","createMediaElementSource","AudioElement","volume","containerWidth","clientWidth","lastPos","createWrapper","createElements","wrapper","style","display","userSelect","webkitUserSelect","overflowX","overflowY","setupWrapperEvents","handleEvent","preventDefault","bbox","getBoundingClientRect","clientX","left","scrollLeft","scrollWidth","tagName","toLowerCase","classList","contains","parentNode","onMouseUp","stopPropagation","resetScroll","el","styles","prop","percent","recenterOnPosition","immediate","half","rate","updateWidth","minPxDelta","pos","newPos","updateProgress","drawSelection","mark0","mark1","eraseSelection","eraseSelectionMarks","Canvas","waveCanvas","zIndex","progressWave","overflow","borderRight","progressCanvas","selectionZIndex","selectionCanvas","waveCc","getContext","progressCc","selectionCc","cc","canvas","clearRect","$","fillStyle","halfH","coef","scale","beginPath","moveTo","h","lineTo","fill","fillRect","markEl","className","cursor","offsetWidth","top","offsetHeight","backgroundColor","getElementById","title","regionEl","x"],"mappings":"AAAA,YAEA,IAAIA,aACAC,eACIC,OAAgB,IAChBC,UAAgB,OAChBC,cAAgB,OAChBC,YAAgB,OAChBC,eAAgB,OAChBC,iBAAiB,EACjBC,qBAAqB,EACrBC,qBAAsB,OACtBC,YAAgB,EAChBC,YAAgB,EAChBC,WAAgB,EAChBC,YAAgB,GAChBC,WAAgBC,OAAOC,iBACvBC,YAAgB,EAChBC,cAAgB,EAChBC,WAAgB,EAChBC,aAAgB,KAChBC,UAAgB,KAChBC,eAAgB,EAChBC,eAAgB,EAChBC,UAAgB,EAChBC,UAAgB,EAChBC,SAAgB,SAChBC,QAAgB,kBAGpBC,KAAM,SAAUC,GAQZ,GANAC,KAAKD,OAAS7B,WAAW+B,KAAKC,UAAWF,KAAK7B,cAAe4B,GAE7DC,KAAKT,UAAY,gBAAmBQ,GAAOR,UACvCY,SAASC,cAAcJ,KAAKD,OAAOR,WACnCS,KAAKD,OAAOR,WAEXS,KAAKT,UACN,KAAM,IAAIc,OAAM,6CAIpBL,MAAKM,WACLN,KAAKO,KAAK,SAAUP,KAAKQ,UAAUC,KAAKT,OACxCA,KAAKO,KAAK,iBAAkBP,KAAKU,YAAYD,KAAKT,OAGlDA,KAAKW,WAILX,KAAKY,YAAc,EAEnBZ,KAAKa,SAAU,EAEfb,KAAKc,iBACLd,KAAKe,eACLf,KAAKgB,iBAGTF,eAAgB,WAEZ,GAAIG,GAAKjB,KACLkB,EAAe,WACfD,EAAGE,UAAU,eAEjBhB,UAASiB,iBAAiB,YAAaF,GACvCf,SAASiB,iBAAiB,UAAWF,GACrClB,KAAKqB,GAAG,UAAW,WACflB,SAASmB,oBAAoB,YAAaJ,GAC1Cf,SAASmB,oBAAoB,UAAWJ,MAQhDK,YAAa,SAAUC,GACnB,GAAIP,GAAKjB,KAELyB,EAAQtB,SAASuB,cAAc,QACnCD,GAAME,UAAW,EACjBF,EAAMG,UAAW,EACjBH,EAAMI,IAAML,EAEZC,EAAML,iBAAiB,QAAS,WAC5BH,EAAGE,UAAU,QAAS,iCAG1BM,EAAML,iBAAiB,UAAW,WAC9BH,EAAGE,UAAU,kBAGjB,IAAIW,GAAY9B,KAAKT,UAAUa,cAAc,QAM7C,OALI0B,IACA9B,KAAKT,UAAUwC,YAAYD,GAE/B9B,KAAKT,UAAUyC,YAAYP,GAEpBA,GAGXV,aAAc,WACV,GAAIE,GAAKjB,IAETA,MAAKiC,OAASC,OAAOC,OAAOjE,WAAWkE,OAAOpC,KAAKD,OAAOH,WAC1DI,KAAKiC,OAAOnC,KAAKE,KAAKT,UAAWS,KAAKD,QAEtCC,KAAKiC,OAAOZ,GAAG,SAAU,WACrBJ,EAAGoB,aACHpB,EAAGgB,OAAOK,SAASrB,EAAGpB,QAAQ0C,uBAGlCvC,KAAKqB,GAAG,WAAY,SAAUiB,GAC1BrB,EAAGgB,OAAOK,SAASA,KAIvBtC,KAAKiC,OAAOZ,GAAG,YAAa,SAAUiB,GAClCE,WAAW,WACPvB,EAAGwB,OAAOH,IACX,KAIPtC,KAAKiC,OAAOZ,GAAG,gBAAiB,SAAUqB,GACtC,GAAIC,GAAO1B,EAAGX,QAAQoC,EAClBC,IACAA,EAAKC,WAKT5C,KAAKD,OAAOP,gBACZQ,KAAKiC,OAAOZ,GAAG,OAAQ,SAAUwB,GAC7B5B,EAAG6B,UAAW,EACd7B,EAAG8B,gBAAgBF,KAGvB7C,KAAKiC,OAAOZ,GAAG,aAAc,WACzBJ,EAAG+B,oBAIXhD,KAAKiC,OAAOZ,GAAG,YAAa,SAAUwB,EAAMF,GACxCA,EAAKxB,UAAU,OAAQ0B,KAI3B7C,KAAKiC,OAAOZ,GAAG,UAAW,SAAU4B,GAChChC,EAAGE,UAAU,UAAW8B,GACxBhC,EAAG6B,UAAW,KAItB9B,cAAe,WACX,GAAIC,GAAKjB,IAELA,MAAKH,SACLG,KAAKH,QAAQqD,UAGjBlD,KAAKH,QAAUqC,OAAOC,OAAOjE,WAAW8B,KAAKD,OAAOF,UAEpDG,KAAKH,QAAQwB,GAAG,OAAQ,WACpBJ,EAAGE,UAAU,QACbF,EAAGkC,yBAGPnD,KAAKH,QAAQwB,GAAG,SAAU,WACtBJ,EAAGE,UAAU,WAGjB,KACInB,KAAKH,QAAQC,KAAKE,KAAKD,QACzB,MAAOkD,GACY,wDAAbA,EAAEG,UACFpD,KAAKD,OAAOF,QAAU,eACtBG,KAAKH,QAAU,KACfG,KAAKgB,mBAKjBmC,qBAAsB,WAClB,GAAIlC,GAAKjB,KACLqD,EAAepE,OAAOqE,uBAClBrE,OAAOsE,4BACXC,EAAQ,WACHvC,EAAGpB,QAAQ4D,aACZxC,EAAGE,UAAU,WAAYF,EAAGpB,QAAQ0C,qBACpCc,EAAaG,IAGrBA,MAGJE,YAAa,WACT,MAAO1D,MAAKH,QAAQ6D,eAGxBC,eAAgB,WACZ,MAAO3D,MAAKH,QAAQ8D,kBAGxBC,KAAM,SAAUC,EAAOC,GACnB9D,KAAKH,QAAQ+D,KAAKC,EAAOC,IAG7BC,MAAO,WACH/D,KAAKH,QAAQkE,SAGjBC,UAAW,WACPhE,KAAKH,QAAQ4D,WAAazD,KAAK4D,OAAS5D,KAAK+D,SAGjDE,mBAAoB,WAChB,GAAIC,GAAMlE,KAAKmE,cACH,QAARD,IACAlE,KAAKyC,OAAOyB,EAAIE,iBAChBpE,KAAKgE,cAIbK,aAAc,SAAUC,GACpBtE,KAAKuE,KAAKD,IAAYtE,KAAKD,OAAOjB,aAGtC0F,YAAa,SAAUF,GACnBtE,KAAKuE,KAAKD,GAAWtE,KAAKD,OAAOjB,aAGrCyF,KAAM,SAAUE,GACZ,GAAIC,GAAU1E,KAAK0E,QAAQD,GACvBnC,EAAWoC,EAAQ,GAAKA,EAAQ,EAEpC1E,MAAKyC,OAAOH,IAGhBqC,cAAe,SAAUrC,GACrBtC,KAAKyC,OAAOH,GACZtC,KAAKiC,OAAO2C,SAAStC,IAGzBG,OAAQ,SAAUH,GACd,GAAIuC,GAAS7E,KAAKH,QAAQ4D,WAEtBqB,EAAkB9E,KAAKD,OAAOX,YAC9ByF,KACA7E,KAAKD,OAAOX,cAAe,EAE3BY,KAAKY,YAAcZ,KAAKH,QAAQkF,YAChC/E,KAAKH,QAAQmF,UAAU,IAE3BhF,KAAK4D,KAAMtB,EAAWtC,KAAKiC,OAAOgD,MAASjF,KAAKkF,cAC5CL,IACA7E,KAAK+D,QACL/D,KAAKH,QAAQmF,UAAUhF,KAAKY,cAEhCZ,KAAKD,OAAOX,aAAe0F,EAC3B9E,KAAKmB,UAAU,OAAQmB,IAG3B6C,KAAM,WACFnF,KAAK+D,QACL/D,KAAKyC,OAAO,GACZzC,KAAKiC,OAAOK,SAAS,IASzB0C,UAAW,SAAUI,GACjBpF,KAAKH,QAAQmF,UAAUI,IAS3BC,WAAY,WACJrF,KAAKa,SAGLb,KAAKH,QAAQmF,UAAUhF,KAAKY,aAC5BZ,KAAKa,SAAU,IAIfb,KAAKY,YAAcZ,KAAKH,QAAQkF,YAChC/E,KAAKH,QAAQmF,UAAU,GACvBhF,KAAKa,SAAU,IAIvByE,aAAc,WACVtF,KAAKD,OAAOX,cAAgBY,KAAKD,OAAOX,aACxCY,KAAKqC,cAGTM,KAAM,SAAU4C,GACZ,GAAItE,GAAKjB,KAELwF,EAAOtH,WAAW+B,KAAKC,QACvBwC,GAAIxE,WAAW+B,KAAKwF,QACpBR,MAAOjF,KAAKD,OAAOlB,aACpB0G,EAQH,IANIC,EAAKE,aAAeF,EAAKG,WACzBH,EAAKG,SAAWH,EAAKE,WAAa1F,KAAK0D,eAE3C8B,EAAKE,WAAaF,EAAKG,SAAW3F,KAAK0D,cAGnC8B,EAAK9C,KAAM1C,MAAKM,QAChB,MAAON,MAAKM,QAAQkF,EAAK9C,IAAIkD,OAAOJ,EAInCA,GAAKG,WACNH,EAAKG,SAAW3F,KAAK2D,iBACrB6B,EAAKE,WAAaF,EAAKG,SAAW3F,KAAK0D,cAG3C,IAAIf,GAAOT,OAAOC,OAAOjE,WAAW2H,KA0CpC,OAzCAlD,GAAK7C,KAAK0F,GAGNxF,KAAK8C,UACLH,EAAKmD,KAAO,UACZnD,EAAKtB,GAAG,OAAQ,SAAUwB,GACtB5B,EAAG8E,sBAAsBlD,EAAMF,MAGnCA,EAAKtB,GAAG,OAAQ,SAAUwB,GACtB5B,EAAG+E,SAASnD,EAAMF,KAI1BA,EAAKtB,GAAG,SAAU,WACdJ,EAAGgB,OAAOgE,WAAWtD,GACrB1B,EAAGE,UAAU,eAAgBwB,KAEjCA,EAAKtB,GAAG,SAAU,WACdJ,EAAGgB,OAAOiE,WAAWvD,SACd1B,GAAGX,QAAQqC,EAAKD,IACvBzB,EAAGE,UAAU,eAAgBwB,KAGjC3C,KAAKiC,OAAOkE,QAAQxD,GACpB3C,KAAKiC,OAAOZ,GAAG,YAAa,SAAUsB,EAAMM,GACxCN,EAAKxB,UAAU,OAAQ8B,GACvBhC,EAAGE,UAAU,YAAawB,EAAMM,KAEpCjD,KAAKiC,OAAOZ,GAAG,aAAc,SAAUsB,EAAMM,GACzCN,EAAKxB,UAAU,QAAS8B,GACxBhC,EAAGE,UAAU,aAAcwB,EAAMM,KAErCjD,KAAKiC,OAAOZ,GAAG,aAAc,SAAUsB,EAAMM,GACzCN,EAAKxB,UAAU,QAAS8B,GACxBhC,EAAGE,UAAU,aAAcwB,EAAMM,KAGrCjD,KAAKM,QAAQqC,EAAKD,IAAMC,EACxB3C,KAAKmB,UAAU,SAAUwB,GAElBA,GAGXyD,WAAY,WACRlE,OAAOmE,KAAKrG,KAAKM,SAASgG,QAAQ,SAAU5D,GACxC1C,KAAKM,QAAQoC,GAAIE,UAClB5C,MACHA,KAAKM,YAGTiG,cAAe,WACXrE,OAAOmE,KAAKrG,KAAKW,SAAS2F,QAAQ,SAAU5D,GACxC1C,KAAKwG,OAAOxG,KAAKW,QAAQ+B,KAC1B1C,OAGPyG,aAAc,WACVvE,OAAOmE,KAAKrG,KAAKW,SAAS2F,QAAQ,SAAU5D,GACxC1C,KAAKW,QAAQ+B,GAAIE,UAClB5C,MACHA,KAAKW,YAGT6F,OAAQ,SAAUjB,GACd,GAAItE,GAAKjB,KAELwF,EAAOtH,WAAW+B,KAAKC,QACvBwC,GAAIxE,WAAW+B,KAAKwF,SACrBF,EAMH,IAJAC,EAAKpB,gBAAkBoB,EAAKkB,cAAgB1G,KAAK0D,cACjD8B,EAAKmB,cAAgBnB,EAAKoB,YAAc5G,KAAK0D,cAGzC8B,EAAK9C,KAAM1C,MAAKW,QAChB,MAAOX,MAAKW,QAAQ6E,EAAK9C,IAAIkD,OAAOJ,EAGxC,IAAIgB,GAAStE,OAAOC,OAAOjE,WAAW2I,OA+BtC,OA9BAL,GAAO1G,KAAK0F,GAEZgB,EAAOnF,GAAG,SAAU,WAChBJ,EAAGgB,OAAO6E,aAAaN,GACvBvF,EAAGE,UAAU,iBAAkBqF,KAEnCA,EAAOnF,GAAG,SAAU,WAChBJ,EAAGgB,OAAO8E,aAAaP,GACvBvF,EAAGE,UAAU,iBAAkBqF,SACxBvF,GAAGN,QAAQ6F,EAAO9D,MAG7B1C,KAAKiC,OAAO+E,UAAUR,GAEtBxG,KAAKiC,OAAOZ,GAAG,cAAe,SAAUmF,EAAQvD,GAC5CuD,EAAOrF,UAAU,OAAQ8B,GACzBhC,EAAGE,UAAU,cAAeqF,EAAQvD,KAExCjD,KAAKiC,OAAOZ,GAAG,eAAgB,SAAUmF,EAAQvD,GAC7CuD,EAAOrF,UAAU,QAAS8B,GAC1BhC,EAAGE,UAAU,eAAgBqF,EAAQvD,KAEzCjD,KAAKiC,OAAOZ,GAAG,eAAgB,SAAUmF,EAAQvD,GAC7CuD,EAAOrF,UAAU,QAAS8B,GAC1BhC,EAAGE,UAAU,eAAgBqF,EAAQvD,KAGzCjD,KAAKW,QAAQ6F,EAAO9D,IAAM8D,EAC1BxG,KAAKmB,UAAU,iBAAkBqF,GAE1BA,GAIX9B,QAAS,SAAUD,GACf,GAAIkB,GAAW3F,KAAK2D,kBAAoB,EACpCsD,EAAWjH,KAAK0D,eAAiB,CAErC,OADAiC,GAAWuB,KAAKC,IAAI,EAAGD,KAAKE,IAAIH,EAAUtB,GAAYlB,GAAU,MACvDkB,EAAUsB,IAGvB5E,WAAY,WACR,GAAIrC,KAAKD,OAAOZ,aAAea,KAAKD,OAAOX,aACvC,GAAIiI,GAASrH,KAAKiC,OAAOqF,eAEzBD,GAASH,KAAKK,MAAMvH,KAAK0D,cAAgB1D,KAAKD,OAAOhB,YAAciB,KAAKD,OAAOf,WAEnFgB,MAAKkF,aAAemC,EAASrH,KAAK0D,cAElC1D,KAAKiC,OAAOuF,UAAUxH,KAAKH,QAAQ4H,SAASJ,GAASA,GACrDrH,KAAKmB,UAAU,WAGnBuG,cAAe,WACX,GAAIzG,GAAKjB,IACTA,MAAKkF,aAAelF,KAAKD,OAAOhB,YAAciB,KAAKD,OAAOf,UAC1D,IAEI2I,GAFAC,EAAY,EAAI5H,KAAKkF,aACrB2C,EAAW,CAGf7H,MAAK8H,UAAY,SAAUC,GACvB,KAAIA,EAAOF,GAA8BD,EAAlBG,EAAOF,GAA9B,CAGAA,EAAWE,CACX,IAAId,GAAWhG,EAAGyC,aAClB,IAAesE,IAAXf,EAAqB,CACrB,GAAII,GAASH,KAAKK,MAAMN,EAAWhG,EAAGiE,aACtCyC,GAAQA,GAAS,GAAIM,YAAWZ,OAEhCM,GAAQA,MACRN,EAASM,EAAMN,MAEnB,IAAIa,MAAWjH,EAAGpB,QAAQ0C,oBAAsB8E,EAC3CM,GAAMO,KACPP,EAAMO,GAAShK,WAAW+B,KAAKkH,IAAIlG,EAAGpB,QAAQsI,WAAY,KAC1DlH,EAAGgB,OAAOmG,SAASf,GACnBpG,EAAGgB,OAAOoG,YACVpH,EAAGgB,OAAOqG,SAASX,EAAO,QAIlC3H,KAAKH,QAAQwB,GAAG,eAAgBrB,KAAK8H,YAMzCS,gBAAiB,SAAUC,GACvB,GAAIvH,GAAKjB,IACTA,MAAKH,QAAQ4I,kBAAkBD,EAAa,SAAUE,GAClDzH,EAAG0H,kBAAkBD,IACtB,WACCzH,EAAGE,UAAU,QAAS,iCAO9BwH,kBAAmB,SAAUC,GACzB5I,KAAK6I,QAGsB,kBAAvB7I,KAAKD,OAAOF,UACZG,KAAKD,OAAOF,QAAU,iBACtBG,KAAKgB,iBAEThB,KAAKH,QAAQiJ,KAAKF,GAElB5I,KAAKqC,aACLrC,KAAKmB,UAAU,UAQnB4H,SAAU,SAAUC,GAChB,GAAI/H,GAAKjB,KAELiJ,EAAS,GAAIC,WACjBD,GAAO7H,iBAAiB,WAAY,SAAU6B,GAC1ChC,EAAGkI,WAAWlG,KAElBgG,EAAO7H,iBAAiB,OAAQ,SAAU6B,GACtChC,EAAG4H,QACH5H,EAAGsH,gBAAgBtF,EAAEmG,OAAOC,UAEhCJ,EAAO7H,iBAAiB,QAAS,WAC7BH,EAAGE,UAAU,QAAS,wBAE1B8H,EAAOK,kBAAkBN,IAM7BF,KAAM,SAAUtH,EAAKmG,GACjB,OAAQ3H,KAAKD,OAAOF,SAChB,IAAK,iBAAkB,MAAOG,MAAKuJ,WAAW/H,EAC9C,KAAK,gBAAiB,MAAOxB,MAAKwJ,WAAWhI,EAC7C,KAAK,eAAgB,MAAOxB,MAAKyJ,iBAAiBjI,EAAKmG,KAO/D4B,WAAY,SAAU/H,GAGlB,MAFAxB,MAAK6I,QAEE7I,KAAK0J,oBAAoBlI,EAAKxB,KAAKuI,gBAAgB9H,KAAKT,QAMnEwJ,WAAY,SAAUhI,GAClB,GAAIP,GAAKjB,IAGkB,kBAAvBA,KAAKD,OAAOF,UACZG,KAAKD,OAAOF,QAAU,gBACtBG,KAAKgB,iBAGThB,KAAK6I,QACL7I,KAAK0H,gBACL1H,KAAKyB,MAAQzB,KAAKuB,YAAYC,GAG9BxB,KAAKO,KAAK,cAAe,WAErBU,EAAGpB,QAAQiJ,KAAK7H,EAAGQ,SAGvBe,WAAWxC,KAAKmB,UAAUV,KAAKT,KAAM,SAAU,IAGnDyJ,iBAAkB,SAAUjI,EAAKmG,GAC7B,GAAI1G,GAAKjB,IAGkB,iBAAvBA,KAAKD,OAAOF,UACZG,KAAKD,OAAOF,QAAU,eACtBG,KAAKgB,iBAGThB,KAAK6I,QACL7I,KAAKyB,MAAQzB,KAAKuB,YAAYC,GAE9BxB,KAAKO,KAAK,gBAAiB,WACvBU,EAAGpB,QAAQiJ,KAAK7H,EAAGQ,MAAOkG,GAC1B1G,EAAGoB,aACHpB,EAAGE,UAAU,YAIrBuI,oBAAqB,SAAUlI,EAAKmI,GAChC,GAAI1I,GAAKjB,KACL4J,EAAO1L,WAAW+B,KAAK2J,MACvBpI,IAAKA,EACLqI,aAAc,eASlB,OAPAD,GAAKvI,GAAG,WAAY,SAAU4B,GAC1BhC,EAAGkI,WAAWlG,KAElB2G,EAAKvI,GAAG,UAAWsI,GACnBC,EAAKvI,GAAG,QAAS,SAAU4B,GACvBhC,EAAGE,UAAU,QAAS,cAAgB8B,EAAEmG,OAAOU,cAE5CF,GAGXT,WAAY,SAAUlG,GAClB,GAAIA,EAAE8G,iBACF,GAAIC,GAAkB/G,EAAEgH,OAAShH,EAAEiH,UAInCF,GAAkB/G,EAAEgH,QAAUhH,EAAEgH,OAAS,IAE7CjK,MAAKmB,UAAU,UAAW+F,KAAKK,MAAwB,IAAlByC,GAAwB/G,EAAEmG,SAGnE5I,UAAW,WACP,GAAIS,GAAKjB,KACL6H,EAAW,CAEf7H,MAAKH,QAAQwB,GAAG,OAAQ,WAEpBa,OAAOmE,KAAKpF,EAAGX,SAASgG,QAAQ,SAAU5D,GACtCzB,EAAGX,QAAQoC,GAAIyH,QAAS,MAIhCnK,KAAKH,QAAQwB,GAAG,eAAgB,SAAU0G,GACtC7F,OAAOmE,KAAKpF,EAAGX,SAASgG,QAAQ,SAAU5D,GACtC,GAAI0H,GAASnJ,EAAGX,QAAQoC,EACnB0H,GAAOD,QACJC,EAAOzE,UAAYoC,GAAQqC,EAAOzE,UAAYkC,IAE9CuC,EAAOD,QAAS,EAEhBlJ,EAAGE,UAAU,OAAQiJ,GACrBA,EAAOjJ,UAAU,cAI7B0G,EAAWE,KAInBrH,YAAa,WACT,GAAIO,GAAKjB,IACTA,MAAKH,QAAQwB,GAAG,OAAQ,WACpBa,OAAOmE,KAAKpF,EAAGN,SAAS2F,QAAQ,SAAU5D,GACtCzB,EAAGN,QAAQ+B,GAAI2H,SAAU,EACzBpJ,EAAGN,QAAQ+B,GAAI4H,UAAW,MAGlCtK,KAAKH,QAAQwB,GAAG,eAAgB,SAAU0G,GACtC7F,OAAOmE,KAAKpF,EAAGN,SAAS2F,QAAQ,SAAU5D,GACtC,GAAI8D,GAASvF,EAAGN,QAAQ+B,IACnB8D,EAAO6D,SAAW7D,EAAOE,eAAiBqB,GAAQvB,EAAOI,aAAemB,IACzE9G,EAAGE,UAAU,YAAaqF,GAC1BA,EAAOrF,UAAU,MACjBqF,EAAO6D,SAAU,IAEhB7D,EAAO8D,UAAY9D,EAAO6D,SAAW7D,EAAOI,YAAcmB,IAC3D9G,EAAGE,UAAU,aAAcqF,GAC3BA,EAAOrF,UAAU,OACjBqF,EAAO8D,UAAW,QASlCzB,MAAO,WACC7I,KAAK8H,YACL9H,KAAKuK,GAAG,WAAYvK,KAAK8H,WACzB9H,KAAK8H,UAAY,MAGjB9H,KAAKH,UAAYG,KAAKH,QAAQ4D,aAC9BzD,KAAKmF,OACLnF,KAAKH,QAAQ2K,oBAEjBxK,KAAKoG,aACLpG,KAAKyG,eACLzG,KAAKiC,OAAOmG,SAAS,GACrBpI,KAAKiC,OAAOuF,WAAYH,OAAQrH,KAAKiC,OAAOqF,YAAc,IAM9DpE,QAAS,WACLlD,KAAKmB,UAAU,WACfnB,KAAKoG,aACLpG,KAAKyG,eACLzG,KAAKyK,QACLzK,KAAKH,QAAQqD,UACblD,KAAKiC,OAAOiB,UACRlD,KAAKyB,OACLzB,KAAKT,UAAUwC,YAAY/B,KAAKyB,QAIxCsE,sBAAuB,SAAU2E,EAAU/H,GACvC,GAAIgI,EAEAA,GADAhI,EAAKD,IAAM1C,KAAK4K,SAASlI,IAErB0B,gBAAmBsG,EAAS/D,cAC5BA,cAAiB3G,KAAK6K,SAASnF,aAI/BtB,gBAAmBpE,KAAK4K,SAASlF,WACjCiB,cAAiB+D,EAAS/D,eAGlC3G,KAAK+C,gBAAgB4H,IAGzB5H,gBAAiB,SAAU4H,GACvB,GAAI1J,GAAKjB,KACL8K,EAAWH,EAAUvG,gBACrB2G,EAAWJ,EAAUhE,cACrBqE,EAAQhL,KAAKD,OAAOvB,eACpByG,EAAQ,CAMZ,IALIjF,KAAKD,OAAOtB,kBACZuM,EAAQhL,KAAKD,OAAOpB,qBACpBsG,EAAQ,GAGR6F,EAAWC,EAAU,CACrB,GAAIE,GAAaH,CACjBA,GAAWC,EACXA,EAAWE,EAGXjL,KAAK4K,SACL5K,KAAK4K,SAAShF,QACVF,WAAYoF,EACZnF,SAAUmF,EAAW9K,KAAK0D,gBAG9B1D,KAAK4K,SAAW5K,KAAK2C,MACjBsC,MAAOA,EACPS,WAAYoF,EACZnF,SAAUmF,EAAW9K,KAAK0D,cAC1BsH,MAAOA,EACPE,UAAWjK,EAAGlB,OAAOtB,kBAIzBuB,KAAK6K,SACL7K,KAAK6K,SAASjF,QACVF,WAAYqF,EACZpF,SAAUoF,EAAW/K,KAAK0D,gBAG9B1D,KAAK6K,SAAW7K,KAAK2C,MACjBsC,MAAOA,EACPS,WAAYqF,EACZpF,SAAUoF,EAAW/K,KAAK0D,cAC1BsH,MAAOA,EACPE,UAAWjK,EAAGlB,OAAOtB,kBAI7BuB,KAAKiC,OAAOc,gBAAgB+H,EAAUC,GAElC/K,KAAKD,OAAON,eACZO,KAAKH,QAAQkD,gBAAgB+H,EAAUC,GAE3C9J,EAAGE,UAAU,mBAAoBnB,KAAKmE,iBAG1C6B,SAAU,SAAUnD,EAAMF,GACtBA,EAAKiD,QACDF,WAAY7C,EAAK8D,cACjBhB,SAAU9C,EAAK8D,cAAgB3G,KAAK0D,gBAExC1D,KAAKM,QAAQqC,EAAKD,IAAMC,GAG5BK,eAAgB,WACRhD,KAAK4K,UAAY5K,KAAK6K,WACtB7K,KAAKiC,OAAOe,eAAehD,KAAK4K,SAAU5K,KAAK6K,UAE/C7K,KAAK4K,SAAShI,SACd5C,KAAK4K,SAAW,KAEhB5K,KAAK6K,SAASjI,SACd5C,KAAK6K,SAAW,KAEZ7K,KAAKD,OAAON,eACZO,KAAKH,QAAQmD,iBAEjBhD,KAAKmB,UAAU,mBAAoBnB,KAAKmE,kBAIhDgH,oBAAqB,WACjBnL,KAAKD,OAAON,eAAiBO,KAAKD,OAAON,cACrCO,KAAKD,OAAON,cACRO,KAAK4K,UAAY5K,KAAK6K,UACtB7K,KAAK+C,iBACDqB,gBAAiBpE,KAAK4K,SAASlF,WAC/BiB,cAAe3G,KAAK6K,SAASnF,aAIrC1F,KAAKH,QAAQmD,kBAIrBmB,aAAc,WACV,MAAKnE,MAAK4K,UAAa5K,KAAK6K,UAExBzG,gBAAiBpE,KAAK4K,SAASlF,WAC/BgB,cAAe1G,KAAK4K,SAASjF,SAC7BgB,cAAe3G,KAAK6K,SAASnF,WAC7BkB,YAAa5G,KAAK6K,SAASlF,SAC3ByF,UAAWpL,KAAK4K,SAASS,WACzBC,QAAStL,KAAK6K,SAASQ,YAPkB,MAWjDE,kBAAmB,WACfvL,KAAKiC,OAAOtC,UAAW,GAG3B6L,mBAAoB,WAChBxL,KAAKiC,OAAOtC,UAAW,GAG3B8L,kBAAmB,WACfzL,KAAKiC,OAAOtC,UAAYK,KAAKiC,OAAOtC,UAM5CzB,YAAW2H,MACP1H,eACIuE,GAAI,KACJiD,SAAU,EACVD,WAAY,EACZT,MAAO,EACP+F,MAAO,OACPE,WAAW,GAGfpL,KAAM,SAAUyF,GAIZ,MAHAvF,MAAK0L,MACDxN,WAAW+B,KAAKC,UAAWF,KAAK7B,cAAeoH,IAE5CvF,MAGXqL,SAAU,WACN,UACOrL,KAAK2F,SAAW,KAClB,QAAU3F,KAAK2F,SAAW,KAAKgG,MAAM,KACxCC,KAAK,MAGXF,MAAO,SAAUnG,GACbrD,OAAOmE,KAAKd,GAASe,QAAQ,SAAUuF,GAC/BA,IAAO7L,MAAK7B,gBACZ6B,KAAK6L,GAAOtG,EAAQsG,KAEzB7L,OAGP4F,OAAQ,SAAUL,GACdvF,KAAK0L,MAAMnG,GACXvF,KAAKmB,UAAU,WAGnByB,OAAQ,WACJ5C,KAAKmB,UAAU,UACfnB,KAAKyK,UAMbvM,WAAW2I,QACP1I,eACIuE,GAAI,KACJgE,cAAe,EACfE,YAAa,EACbxC,gBAAiB,EACjBuC,cAAe,EACfqE,MAAO,wBAGXlL,KAAM,SAAUyF,GAIZ,MAHAvF,MAAK0L,MACDxN,WAAW+B,KAAKC,UAAWF,KAAK7B,cAAeoH,IAE5CvF,MAGX0L,MAAO,SAAUnG,GACbrD,OAAOmE,KAAKd,GAASe,QAAQ,SAAUuF,GAC/BA,IAAO7L,MAAK7B,gBACZ6B,KAAK6L,GAAOtG,EAAQsG,KAEzB7L,OAGP4F,OAAQ,SAAUL,GACdvF,KAAK0L,MAAMnG,GACXvF,KAAKmB,UAAU,WAGnByB,OAAQ,WACJ5C,KAAKmB,UAAU,UACfnB,KAAKyK,UAKbvM,WAAW4N,UACPzK,GAAI,SAAU0K,EAAOC,GACZhM,KAAKiM,WAAYjM,KAAKiM,YAE3B,IAAIA,GAAWjM,KAAKiM,SAASF,EACxBE,KACDA,EAAWjM,KAAKiM,SAASF,OAE7BE,EAASC,KAAKF,IAGlBzB,GAAI,SAAUwB,EAAOC,GACjB,GAAKhM,KAAKiM,SAAV,CAEA,GAAIA,GAAWjM,KAAKiM,SAASF,EAC7B,IAAIE,EACA,GAAID,EACA,IAAK,GAAIG,GAAIF,EAAS5E,OAAS,EAAG8E,GAAK,EAAGA,IAClCF,EAASE,IAAMH,GACfC,EAASG,OAAOD,EAAG,OAI3BF,GAAS5E,OAAS,IAK9BoD,MAAO,WACHzK,KAAKiM,SAAW,MAGpB1L,KAAM,SAAUwL,EAAOM,GACnB,GAAIpL,GAAKjB,KACLgM,EAAK,WACLK,IACA7J,WAAW,WACPvB,EAAGsJ,GAAGwB,EAAOC,IACd,GAEPhM,MAAKqB,GAAG0K,EAAOC,IAGnB7K,UAAW,SAAU4K,GACjB,GAAK/L,KAAKiM,SAAV,CACA,GAAIA,GAAWjM,KAAKiM,SAASF,GACzBO,EAAOC,MAAMC,UAAUb,MAAMc,KAAKC,UAAW,EACjDT,IAAYA,EAAS3F,QAAQ,SAAU0F,GACnCA,EAAGN,MAAM,KAAMY,QAM3BpO,WAAW+B,MACPC,OAAQ,SAAUyM,GACd,GAAIC,GAAUL,MAAMC,UAAUb,MAAMc,KAAKC,UAAW,EAMpD,OALAE,GAAQtG,QAAQ,SAAUuG,GACtB3K,OAAOmE,KAAKwG,GAAQvG,QAAQ,SAAUuF,GAClCc,EAAKd,GAAOgB,EAAOhB,OAGpBc,GAGXlH,MAAO,WACH,MAAO,cAAgByB,KAAK4F,SAASC,SAAS,IAAIC,UAAU,IAGhE7F,IAAK,SAAU8F,EAAQ7F,GAEnB,IAAK,GADDD,IAAOa,IACFmE,EAAI,EAAGe,EAAMD,EAAO5F,OAAY6F,EAAJf,EAASA,IAAK,CAC/C,GAAIgB,GAAMF,EAAOd,EACN,OAAP/E,IACA+F,EAAMjG,KAAKkG,IAAID,EAAM/F,IAErB+F,EAAMhG,IAAOA,EAAMgG,GAE3B,MAAOhG,IAGXyC,KAAM,SAAUrE,GACZ,GAAIqE,GAAO1H,OAAOC,OAAOjE,WAAW4N,UAChCuB,EAAM,GAAIC,gBACVC,GAAW,CA0Bf,OAzBAF,GAAIG,KAAKjI,EAAQkI,QAAU,MAAOlI,EAAQ/D,KAAK,GAC/C6L,EAAIxD,aAAetE,EAAQsE,aAC3BwD,EAAIjM,iBAAiB,WAAY,SAAU6B,GACvC2G,EAAKzI,UAAU,WAAY8B,GACvBA,EAAE8G,kBAAoB9G,EAAEgH,QAAUhH,EAAEiH,QACpCqD,GAAW,KAGnBF,EAAIjM,iBAAiB,OAAQ,SAAU6B,GAC9BsK,GACD3D,EAAKzI,UAAU,WAAY8B,GAE/B2G,EAAKzI,UAAU,OAAQ8B,GAEnB,KAAOoK,EAAIK,QAAU,KAAOL,EAAIK,OAChC9D,EAAKzI,UAAU,UAAWkM,EAAIM,SAAU1K,GAExC2G,EAAKzI,UAAU,QAAS8B,KAGhCoK,EAAIjM,iBAAiB,QAAS,SAAU6B,GACpC2G,EAAKzI,UAAU,QAAS8B,KAE5BoK,EAAIO,OACJhE,EAAKyD,IAAMA,EACJzD,GAMXiE,SAAU,SAAUC,EAAMC,EAAMxI,GAC5B,GAAIyI,GAAS1B,EAAMjD,EACf4E,EAAU,KACVC,EAAW,CACf3I,KAAYA,KACZ,IAAI4I,GAAQ,WACRD,EAAW3I,EAAQ6I,WAAY,EAAQ,EAAIC,KAAKC,MAChDL,EAAU,KACV5E,EAASyE,EAAKpC,MAAMsC,EAAS1B,GAC7B0B,EAAU1B,EAAO,KAErB,OAAO,YACH,GAAIgC,GAAMD,KAAKC,KACVJ,IAAY3I,EAAQ6I,WAAY,IAAOF,EAAWI,EACvD,IAAIC,GAAYR,GAAQO,EAAMJ,EAY9B,OAXAF,GAAUhO,KACVsM,EAAOI,UACU,GAAb6B,GACAC,aAAaP,GACbA,EAAU,KACVC,EAAWI,EACXjF,EAASyE,EAAKpC,MAAMsC,EAAS1B,GAC7B0B,EAAU1B,EAAO,MACT2B,GAAW1I,EAAQkJ,YAAa,IACxCR,EAAUzL,WAAW2L,EAAOI,IAEzBlF,KAKnBnL,WAAW+B,KAAKC,OAAOhC,WAAYA,WAAW4N,UAC9C5N,WAAW+B,KAAKC,OAAOhC,WAAW2H,KAAM3H,WAAW4N,UACnD5N,WAAW+B,KAAKC,OAAOhC,WAAW2I,OAAQ3I,WAAW4N,UCrkCrD5N,WAAWwQ,UACPC,iBAAkB,IAClBC,QAAS,IAETC,gBAAiB,WACb,IAAM5P,OAAO6P,eAAgB7P,OAAO8P,mBAChC,KAAM,IAAI1O,OACN,uDASR,OALKnC,YAAWwQ,SAASpP,eACrBpB,WAAWwQ,SAASpP,aAAe,IAC/BL,OAAO6P,cAAgB7P,OAAO8P,qBAG/B7Q,WAAWwQ,SAASpP,cAG/BQ,KAAM,SAAUC,GACZC,KAAKD,OAASA,EACdC,KAAKgP,GAAKjP,EAAOT,cAAgBU,KAAK6O,kBAEtC7O,KAAKiP,MAAO,EACZjP,KAAKkP,cAAgB,EACrBlP,KAAKmP,eAAiB,KACtBnP,KAAKoP,aAAc,EAEnBpP,KAAKqP,WAELrP,KAAKsP,mBACLtP,KAAKuP,mBACLvP,KAAKwP,qBACLxP,KAAKyP,gBAAgBzP,KAAKD,OAAOL,YAGrCgQ,kBAAmB,WACX1P,KAAK2P,UACL3P,KAAK2P,QAAQrJ,QAAQ,SAAUsJ,GAC3BA,GAAUA,EAAOC,eAErB7P,KAAK2P,QAAU,OAKvBG,UAAW,WACP9P,KAAK+P,cAAcpE,MAAMc,KAAKC,aAMlCqD,WAAY,SAAUJ,GAClB3P,KAAK0P,oBAEDC,GAAWA,EAAQtI,QACnBrH,KAAK2P,QAAUA,EAGfA,EAAQK,OAAO,SAAUC,EAAMC,GAE3B,MADAD,GAAKE,QAAQD,GACNA,GACRlQ,KAAKoQ,UAAUD,QAAQnQ,KAAKqQ,WAE/BrQ,KAAKoQ,SAASD,QAAQnQ,KAAKqQ,WAInCd,iBAAkB,WACd,GAAItO,GAAKjB,KACLsQ,EAAatQ,KAAK2O,gBAElB3O,MAAKuQ,WADLvQ,KAAKgP,GAAGwB,sBACUxQ,KAAKgP,GAAGwB,sBAAsBF,GAE9BtQ,KAAKgP,GAAGyB,qBAAqBH,GAEnDtQ,KAAKuQ,WAAWJ,QAAQnQ,KAAKgP,GAAG0B,aAChC1Q,KAAKuQ,WAAWI,eAAiB,WAC7B,GAAI5I,GAAO9G,EAAG0C,kBACT1C,EAAGmO,aAAenO,EAAG2H,QAAUb,GAAQ9G,EAAGyC,gBAC3CzC,EAAGmO,aAAc,EACjBnO,EAAGE,UAAU,WAGZF,EAAGwC,aACJxC,EAAG2P,YAAY7I,GACf9G,EAAGE,UAAU,eAAgB4G,MAKzC6I,YAAa,SAAU7I,GACQ,MAAvB/H,KAAKmP,gBACDnP,KAAKkP,eAAiBlP,KAAKmP,gBAC3BnP,KAAK+D,QAIT/D,KAAKiP,MAEDjP,KAAKkP,cAAgBlP,KAAK6Q,WAC1B7Q,KAAKkP,eAAiBlP,KAAK8Q,SAC3B/I,EAAO/H,KAAK8Q,SAEZ9Q,KAAK4D,KAAK5D,KAAK6Q,WAIvB7Q,KAAKkP,cAAgBnH,GAGzByH,mBAAoB,WAChBxP,KAAKoQ,SAAWpQ,KAAKgP,GAAG+B,iBACxB/Q,KAAKoQ,SAASxB,QAAU5O,KAAK4O,QAC7B5O,KAAKgR,aAAe,GAAI/I,YAAWjI,KAAKoQ,SAASa,mBACjDjR,KAAKoQ,SAASD,QAAQnQ,KAAKqQ,WAM/Bf,iBAAkB,WAGVtP,KAAKqQ,SADLrQ,KAAKgP,GAAGkC,WACQlR,KAAKgP,GAAGkC,aAERlR,KAAKgP,GAAGmC,iBAG5BnR,KAAKqQ,SAASF,QAAQnQ,KAAKgP,GAAG0B,cASlC1L,UAAW,SAAUoM,GACjBpR,KAAKqQ,SAASgB,KAAKC,MAAQF,GAS/BrM,UAAW,WACP,MAAO/E,MAAKqQ,SAASgB,KAAKC,OAG9B7I,kBAAmB,SAAUD,EAAamB,EAAU4H,GAChD,GAAItQ,GAAKjB,IACTA,MAAKgP,GAAGwC,gBAAgBhJ,EAAa,SAAUE,GAC3CzH,EAAG2H,OAASF,EACZiB,EAASjB,IACV6I,IAMP9J,SAAU,SAAUJ,GAOhB,IAAK,GANDuB,GAAS5I,KAAK4I,OACd6I,EAAa7I,EAAOvB,OAASA,EAC7BqK,KAAgBD,EAAa,KAAO,EACpCE,EAAW/I,EAAOgJ,iBAClBjK,EAAQ,GAAIkK,cAAaxK,GAEpByK,EAAI,EAAOH,EAAJG,EAAcA,IAE1B,IAAK,GADDC,GAAOnJ,EAAOoJ,eAAeF,GACxB3F,EAAI,EAAO9E,EAAJ8E,EAAYA,IAAK,CAI7B,IAAK,GAHDtI,MAAWsI,EAAIsF,GACf3N,KAASD,EAAQ4N,GACjBtK,EAAM,EACD8K,EAAIpO,EAAWC,EAAJmO,EAASA,GAAKP,EAAY,CAC1C,GAAIJ,GAAQS,EAAKE,EACbX,GAAQnK,EACRA,EAAMmK,GAEEA,EAAQnK,IAChBA,GAAOmK,IAGN,GAALQ,GAAU3K,EAAMQ,EAAMwE,MACtBxE,EAAMwE,GAAKhF,GAKvB,MAAOQ,IAGXpF,kBAAmB,WACf,GAAI0E,GAAWjH,KAAK0D,aACpB,OAAQ1D,MAAK2D,iBAAmBsD,GAAa,GAGjDuD,iBAAkB,WACdxK,KAAKoP,aAAc,EACfpP,KAAK6M,QACL7M,KAAK6M,OAAOgD,cAIpB3M,QAAS,WACLlD,KAAK+D,QACL/D,KAAKyK,QACLzK,KAAK4I,OAAS,KACd5I,KAAK0P,oBACL1P,KAAKwK,mBACLxK,KAAKqQ,SAASR,aACd7P,KAAKuQ,WAAWV,aAChB7P,KAAKoQ,SAASP,cAGlB9M,gBAAiB,SAAUmP,EAAcC,GACrC,GAAIlL,GAAWjH,KAAK0D,aACpB1D,MAAKiP,MAAO,EACZjP,KAAK6Q,UAAY5J,EAAWiL,EAC5BlS,KAAK8Q,QAAU7J,EAAWkL,GAG9BnP,eAAgB,WACZhD,KAAKiP,MAAO,EACZjP,KAAK6Q,UAAY,EACjB7Q,KAAK8Q,QAAU,GASnB3I,SAAU,WAEN,MADAnI,MAAKoQ,SAASgC,sBAAsBpS,KAAKgR,cAClChR,KAAKgR,cAMhB3B,SAAU,aACVvG,KAAM,aAKNnF,eAAgB,WACZ,MAAO,IAMXF,SAAU,WACN,OAAO,GAMXC,YAAa,WACT,MAAO,IAMX+L,gBAAiB,SAAU6B,GACvBtR,KAAKqS,aAAef,GAAS,GAWjC1N,KAAM,aAKNG,MAAO,cAGX7F,WAAW+B,KAAKC,OAAOhC,WAAWwQ,SAAUxQ,WAAW4N,UCpSvD5N,WAAWoU,eAAiBpQ,OAAOC,OAAOjE,WAAWwQ,UAErDxQ,WAAW+B,KAAKC,OAAOhC,WAAWoU,gBAC9BjD,SAAU,WACNrP,KAAKuS,kBAAoB,EACzBvS,KAAKwS,SAAWxS,KAAKyS,UAAYzS,KAAK0S,UAAY1S,KAAKgP,GAAG2D,aAG9D7J,KAAM,SAAUF,GACZ5I,KAAKuS,kBAAoB,EACzBvS,KAAKwS,SAAWxS,KAAKyS,UAAYzS,KAAK0S,UAAY1S,KAAKgP,GAAG2D,YAC1D3S,KAAK4I,OAASA,EACd5I,KAAK4S,gBAGTA,aAAc,WACV5S,KAAKwK,mBACLxK,KAAK6M,OAAS7M,KAAKgP,GAAG6D,qBACtB7S,KAAK6M,OAAOwF,aAAaf,MAAQtR,KAAKqS,aACtCrS,KAAK6M,OAAOjE,OAAS5I,KAAK4I,OAC1B5I,KAAK6M,OAAOsD,QAAQnQ,KAAKoQ,WAG7B3M,SAAU,WACN,MAAOzD,MAAK0S,WAAa1S,KAAKgP,GAAG2D,aAGrCjP,YAAa,WACT,MAAO1D,MAAK4I,OAAO3B,UAWvBrD,KAAM,SAAUC,EAAOC,GAEnB9D,KAAK4S,eAEQ,MAAT/O,IACAA,EAAQ7D,KAAK2D,kBAEN,MAAPG,IAEIA,EADuB,MAAvB9D,KAAKmP,eACCnP,KAAKmP,eAELnP,KAAK0D,eAInB1D,KAAKwS,SAAWxS,KAAKgP,GAAG2D,YACxB3S,KAAKuS,kBAAoB1O,EACzB7D,KAAKyS,UAAYzS,KAAK0S,UAAY1S,KAAKgP,GAAG2D,aAAe7O,EAAMD,GAC/D7D,KAAKkP,cAAgB,GAEjBlP,KAAK6M,OAAOhJ,MACZ7D,KAAK6M,OAAOhJ,MAAM,EAAGA,EAAOC,EAAMD,GAElC7D,KAAK6M,OAAOiG,YAAY,EAAGjP,EAAOC,EAAMD,GAG5C7D,KAAKmB,UAAU,SAMnB4C,MAAO,WACH/D,KAAKmP,eAAiB,KACtBnP,KAAKyS,UAAYzS,KAAK0S,UAAY1S,KAAKgP,GAAG2D,YAEtC3S,KAAK6M,SACD7M,KAAK6M,OAAO1H,KACZnF,KAAK6M,OAAO1H,KAAK,GAEjBnF,KAAK6M,OAAOkG,QAAQ,IAI5B/S,KAAKmB,UAAU,UAGnBwC,eAAgB,WACZ,MAAI3D,MAAKyD,WACEzD,KAAKuS,mBAAqBvS,KAAKyS,UAAYzS,KAAKwS,UAAYxS,KAAKqS,aAEjErS,KAAKuS,mBAAqBvS,KAAKgP,GAAG2D,YAAc3S,KAAKwS,UAAYxS,KAAKqS,cAOrF5C,gBAAiB,SAAU6B,GACvBtR,KAAKqS,aAAef,GAAS,EACzBtR,KAAK6M,SACL7M,KAAK6M,OAAOwF,aAAaf,MAAQtR,KAAKqS,iBCpGlDnU,WAAW8U,cAAgB9Q,OAAOC,OAAOjE,WAAWwQ,UAEpDxQ,WAAW+B,KAAKC,OAAOhC,WAAW8U,eAC9B3D,SAAU,WACN,GAAIpO,GAAKjB,IAGTA,MAAKyB,OACDkR,YAAa,EACb1L,SAAU,EACVpC,QAAQ,EACRwN,aAAc,EACdzO,KAAM,aACNG,MAAO,cAGX/D,KAAKiT,eAAiB,EACtBjT,KAAKqB,GAAG,eAAgB,SAAU0G,GAC1BA,EAAO9G,EAAGgS,iBACVhS,EAAGgS,eAAiBlL,MAKhCe,KAAM,SAAUrH,GACZzB,KAAKwK,mBACLxK,KAAKyB,MAAQA,EACbzB,KAAKiT,eAAiB,EACtBjT,KAAK6M,OAAS7M,KAAKgP,GAAGkE,yBAAyBlT,KAAKyB,OACpDzB,KAAKyB,MAAM4Q,aAAerS,KAAKqS,aAC/BrS,KAAK6M,OAAOsD,QAAQnQ,KAAKoQ,WAG7B3M,SAAU,WACN,MAAOzD,MAAKyB,MAAMoD,QAGtBnB,YAAa,WACT,MAAO1D,MAAKyB,MAAMwF,UAGtBtD,eAAgB,WACZ,MAAO3D,MAAKyB,MAAMkR,aAGtBpQ,kBAAmB,WACf,GAAI0E,GAAWjH,KAAK0D,cAChBqE,EAAO/H,KAAK2D,gBAIhB,OAHIsD,IAAYe,MACZf,EAAWjH,KAAKiT,gBAEZlL,EAAOd,GAAa,GAMhCwI,gBAAiB,SAAU6B,GACvBtR,KAAKqS,aAAef,GAAS,EAC7BtR,KAAKyB,MAAM4Q,aAAerS,KAAKqS,cAWnCzO,KAAM,SAAUC,EAAOC,GACN,MAATD,IACA7D,KAAKyB,MAAMkR,YAAc9O,GAGzB7D,KAAKmP,eADE,MAAPrL,EACsB,KAEAA,EAE1B9D,KAAKyB,MAAMmC,OACX5D,KAAKmB,UAAU,SAMnB4C,MAAO,WACH/D,KAAKmP,eAAiB,KACtBnP,KAAKyB,MAAMsC,QACX/D,KAAKmB,UAAU,YCzFvBjD,WAAWiV,aAAejR,OAAOC,OAAOjE,WAAW8U,eAEnD9U,WAAW+B,KAAKC,OAAOhC,WAAWiV,cAC9BrT,KAAM,SAAUC,GACZC,KAAKD,OAASA,EAEdC,KAAKiP,MAAO,EACZjP,KAAKkP,cAAgB,EACrBlP,KAAKmP,eAAiB,KAEtBnP,KAAKqP,WACLrP,KAAKyP,gBAAgBzP,KAAKD,OAAOL,YAGrCoJ,KAAM,SAAUrH,EAAOkG,GACnB3H,KAAKyB,MAAQA,EACbzB,KAAK2H,MAAQA,EACb3H,KAAKiT,eAAiB,EACtBjT,KAAKyP,gBAAgBzP,KAAKqS,eAG9B5K,SAAU,WACN,MAAOzH,MAAK2H,WAGhB5C,UAAW,WACP,MAAO/E,MAAKyB,MAAM2R,QAGtBpO,UAAW,SAAUmI,GACjBnN,KAAKyB,MAAM2R,OAASjG,GAGxBjK,QAAS,WACLlD,KAAK+D,QACL/D,KAAKyK,QACLzK,KAAKyB,MAAQ,QCpCrBvD,WAAWkE,QACPtC,KAAM,SAAUP,EAAWQ,GACvBC,KAAKT,UAAYA,EACjBS,KAAKD,OAASA,EAEdC,KAAKiF,MAAQ,EACbjF,KAAK5B,OAAS2B,EAAO3B,OAAS4B,KAAKD,OAAOf,WAC1CgB,KAAKqT,eAAiBrT,KAAKT,UAAU+T,YAErCtT,KAAKuT,QAAU,EAEfvT,KAAKwT,gBACLxT,KAAKyT,kBAGTD,cAAe,WACXxT,KAAK0T,QAAU1T,KAAKT,UAAUyC,YAC1B7B,SAASuB,cAAc,SAE3B1B,KAAK2T,MAAM3T,KAAK0T,SACZE,QAAS,QACTjO,SAAU,WACVkO,WAAY,OACZC,iBAAkB,OAClB1V,OAAQ4B,KAAKD,OAAO3B,OAAS,QAG7B4B,KAAKD,OAAOZ,YAAca,KAAKD,OAAOX,eACtCY,KAAK2T,MAAM3T,KAAK0T,SACZzO,MAAO,OACP8O,UAAW,OACXC,UAAW,WAInBhU,KAAKiU,sBAGTC,YAAa,SAAUjR,GACnBA,EAAEkR,gBACF,IAAIC,GAAOpU,KAAK0T,QAAQW,uBACxB,QAASpR,EAAEqR,QAAUF,EAAKG,KAAOvU,KAAK0T,QAAQc,YAAcxU,KAAKyU,aAAgB,GAGrFR,mBAAoB,WAChB,GAAIhT,GAAKjB,IAETA,MAAK0T,QAAQtS,iBAAiB,YAAa,SAAU6B,GAC7ChC,EAAGlB,OAAOJ,UACVsB,EAAGE,UAAU,YAAaF,EAAGiT,YAAYjR,GAAIA,KAIrDjD,KAAK0T,QAAQtS,iBAAiB,UAAW,SAAU6B,GAC3ChC,EAAGlB,OAAOJ,UACVsB,EAAGE,UAAU,UAAW8B,KAIhCjD,KAAK0T,QAAQtS,iBAAiB,WAAY,SAAS6B,IAC3ChC,EAAGlB,OAAOJ,UAAYsB,EAAGlB,OAAOP,iBAEO,YAAnCyD,EAAEmG,OAAOsL,QAAQC,eACZ1R,EAAEmG,OAAOwL,UAAUC,SAAS,gCAKjC5T,EAAGE,UAAU,cAHbF,EAAGE,UAAU,gBAAiB8B,EAAEmG,OAAO0L,WAAWpS,OAQ9D1C,KAAKD,OAAOP,eAAkB,WAC1B,GAAIqD,MAEAkS,EAAY,WACZlS,EAAKuB,gBAAkBvB,EAAK8D,cAAgB,KAEhDxG,UAASiB,iBAAiB,UAAW2T,GACrC9T,EAAGI,GAAG,UAAW,WACblB,SAASmB,oBAAoB,UAAWyT,KAG5C9T,EAAGyS,QAAQtS,iBAAiB,YAAa,SAAU6B,GAC/CJ,EAAKuB,gBAAkBnD,EAAGiT,YAAYjR,KAG1ChC,EAAGyS,QAAQtS,iBAAiB,YAAalD,WAAW+B,KAAK4N,SAAS,SAAU5K,GACxEA,EAAE+R,kBAC0B,MAAxBnS,EAAKuB,kBACLvB,EAAK8D,cAAgB1F,EAAGiT,YAAYjR,GACpChC,EAAGE,UAAU,OAAQ0B,KAE1B,SAIX2E,UAAW,SAAUG,EAAON,GAGxB,GAFArH,KAAKiV,cACLjV,KAAKoI,SAASf,GACVrH,KAAKD,OAAOV,UACZ,GAAI8H,GAAMjJ,WAAW+B,KAAKkH,IAAIQ,OAE9BR,GAAM,CAEVnH,MAAKsI,SAASX,EAAOR,IAGzBwM,MAAO,SAAUuB,EAAIC,GAMjB,MALAjT,QAAOmE,KAAK8O,GAAQ7O,QAAQ,SAAU8O,GAC9BF,EAAGvB,MAAMyB,IAASD,EAAOC,KACzBF,EAAGvB,MAAMyB,GAAQD,EAAOC,MAGzBF,GAGXD,YAAa,WACTjV,KAAK0T,QAAQc,WAAa,GAG9B5P,SAAU,SAAUyQ,GAChB,GAAI1P,GAAW3F,KAAKyU,YAAcY,CAClCrV,MAAKsV,mBAAmB3P,GAAU,IAGtC2P,mBAAoB,SAAU3P,EAAU4P,GACpC,GAAIf,GAAaxU,KAAK0T,QAAQc,WAC1BgB,KAAUxV,KAAKqT,eAAiB,GAChCjK,EAASzD,EAAW6P,EACpB/Q,EAAS2E,EAASoL,CAGtB,KAAKe,GAAa9Q,IAAW+Q,GAAiBA,EAAT/Q,EAAe,CAEhD,GAAIgR,GAAO,CACXhR,GAASyC,KAAKC,KAAKsO,EAAMvO,KAAKE,IAAIqO,EAAMhR,IACxC2E,EAASoL,EAAa/P,EAGZ,GAAVA,IACAzE,KAAK0T,QAAQc,WAAapL,IAIlC9B,SAAU,WACN,MAAOJ,MAAKK,MAAMvH,KAAKqT,eAAiBrT,KAAKD,OAAOf,aAGxDoJ,SAAU,SAAUnD,GACZA,GAASjF,KAAKiF,QAElBjF,KAAKiF,MAAQA,EACbjF,KAAKyU,eAAiBzU,KAAKiF,MAAQjF,KAAKD,OAAOf,YAC/CgB,KAAKqT,eAAiBrT,KAAKT,UAAU+T,YAEjCtT,KAAKD,OAAOZ,YAAca,KAAKD,OAAOX,aACtCY,KAAK2T,MAAM3T,KAAK0T,SACZzO,MAAO,KAGXjF,KAAK2T,MAAM3T,KAAK0T,SACZzO,MAAOjF,KAAKyU,YAAc,OAIlCzU,KAAK0V,gBAGTpT,SAAU,SAAUA,GAChB,GAAIqT,GAAa,EAAI3V,KAAKD,OAAOf,WAC7B4W,EAAM1O,KAAKK,MAAMjF,EAAWtC,KAAKiF,OAAS0Q,CAE9C,IAAIC,EAAM5V,KAAKuT,SAAWqC,EAAM5V,KAAKuT,SAAWoC,EAAY,CAGxD,GAFA3V,KAAKuT,QAAUqC,EAEX5V,KAAKD,OAAOX,aAAc,CAC1B,GAAIyW,MAAY7V,KAAKyU,YAAcnS,EACnCtC,MAAKsV,mBAAmBO,GAG5B7V,KAAK8V,eAAexT,KAI5BY,QAAS,WACLlD,KAAKyK,QACLzK,KAAKT,UAAUwC,YAAY/B,KAAK0T,SAChC1T,KAAK0T,QAAU,MAGnB3Q,gBAAiB,SAAUmP,EAAcC,GACrCnS,KAAKkS,aAAeA,EACpBlS,KAAKmS,WAAaA,EAElBnS,KAAK+V,iBAGT/S,eAAgB,SAAUgT,EAAOC,GAC7BjW,KAAKkS,aAAe,KACpBlS,KAAKmS,WAAa,KAClBnS,KAAKkW,iBACLlW,KAAKmW,oBAAoBH,EAAOC,IAKpCxC,eAAgB,aAEhBiC,YAAa,aAEbpN,SAAU,aAEVD,UAAW,aAEXyN,eAAgB,aAEhB3P,QAAS,aAETD,WAAY,aAEZD,WAAY,aAEZe,UAAW,aAEXD,aAAc,aAEdD,aAAc,aAEdiP,cAAe,aAEfG,eAAgB,aAEhBC,oBAAqB,cAGzBjY,WAAW+B,KAAKC,OAAOhC,WAAWkE,OAAQlE,WAAW4N,UC7OrD5N,WAAWkE,OAAOgU,OAASlU,OAAOC,OAAOjE,WAAWkE,QAEpDlE,WAAW+B,KAAKC,OAAOhC,WAAWkE,OAAOgU,QACrC3C,eAAgB,WACZ,GAAI4C,GAAarW,KAAK0T,QAAQ1R,YAC1BhC,KAAK2T,MAAMxT,SAASuB,cAAc,WAC9BiE,SAAU,WACV2Q,OAAQ,IAIhBtW,MAAKuW,aAAevW,KAAK0T,QAAQ1R,YAC7BhC,KAAK2T,MAAMxT,SAASuB,cAAc,SAC9BiE,SAAU,WACV2Q,OAAQ,EACRE,SAAU,SACVvR,MAAO,IACP7G,OAAQ4B,KAAKD,OAAO3B,OAAS,KAC7BqY,aACIzW,KAAKD,OAAOnB,YAAc,KAC1B,QACAoB,KAAKD,OAAOxB,aACdqN,KAAK,OAIf,IAAI8K,GAAiB1W,KAAKuW,aAAavU,YACnC7B,SAASuB,cAAc,WAGvBiV,EAAkB,CAElB3W,MAAKD,OAAOrB,sBACZiY,EAAkB,EAGtB,IAAIC,GAAkB5W,KAAK0T,QAAQ1R,YAC/BhC,KAAK2T,MAAMxT,SAASuB,cAAc,WAC9BiE,SAAU,WACV2Q,OAAQK,IAIhB3W,MAAK6W,OAASR,EAAWS,WAAW,MACpC9W,KAAK+W,WAAaL,EAAeI,WAAW,MAC5C9W,KAAKgX,YAAcJ,EAAgBE,WAAW,OAGlDpB,YAAa,WACT,GAAIzQ,GAAQiC,KAAKK,MAAMvH,KAAKiF,MAAQjF,KAAKD,OAAOf,aAE5CgB,KAAK6W,OACL7W,KAAK+W,WACL/W,KAAKgX,aACP1Q,QAAQ,SAAU2Q,GAChBA,EAAGC,OAAOjS,MAAQjF,KAAKiF,MACvBgS,EAAGC,OAAO9Y,OAAS4B,KAAK5B,OACxB4B,KAAK2T,MAAMsD,EAAGC,QAAUjS,MAAOA,EAAQ,QACxCjF,MAEHA,KAAKqI,aAGTA,UAAW,WACPrI,KAAK6W,OAAOM,UAAU,EAAG,EAAGnX,KAAKiF,MAAOjF,KAAK5B,QAC7C4B,KAAK+W,WAAWI,UAAU,EAAG,EAAGnX,KAAKiF,MAAOjF,KAAK5B,SAGrDkK,SAAU,SAAUX,EAAOR,GAEvB,GAAIiQ,GAAI,GAAMpX,KAAKD,OAAOf,UAC1BgB,MAAK6W,OAAOQ,UAAYrX,KAAKD,OAAO1B,UACpC2B,KAAK+W,WAAWM,UAAYrX,KAAKD,OAAOzB,aAExC,IAAIgZ,GAAQtX,KAAK5B,OAAS,EACtBmZ,EAAOD,EAAQnQ,EACfqQ,EAAQ,CACRxX,MAAKD,OAAOZ,YAAca,KAAKiF,MAAQ0C,EAAMN,SAC7CmQ,EAAQxX,KAAKiF,MAAQ0C,EAAMN,OAE/B,IAAIA,GAASM,EAAMN,MAEnBrH,MAAK6W,OAAOY,YACZzX,KAAK6W,OAAOa,OAAON,EAAGE,GACtBtX,KAAK+W,WAAWU,YAChBzX,KAAK+W,WAAWW,OAAON,EAAGE,EAC1B,KAAK,GAAInL,GAAI,EAAO9E,EAAJ8E,EAAYA,IAAK,CAC7B,GAAIwL,GAAIzQ,KAAKK,MAAMI,EAAMwE,GAAKoL,EAC9BvX,MAAK6W,OAAOe,OAAOzL,EAAIqL,EAAQJ,EAAGE,EAAQK,GAC1C3X,KAAK+W,WAAWa,OAAOzL,EAAIqL,EAAQJ,EAAGE,EAAQK,GAElD3X,KAAK6W,OAAOe,OAAO5X,KAAKiF,MAAQmS,EAAGE,GACnCtX,KAAK+W,WAAWa,OAAO5X,KAAKiF,MAAQmS,EAAGE,GAEvCtX,KAAK6W,OAAOa,OAAON,EAAGE,GACtBtX,KAAK+W,WAAWW,OAAON,EAAGE,EAC1B,KAAK,GAAInL,GAAI,EAAO9E,EAAJ8E,EAAYA,IAAK,CAC7B,GAAIwL,GAAIzQ,KAAKK,MAAMI,EAAMwE,GAAKoL,EAC9BvX,MAAK6W,OAAOe,OAAOzL,EAAIqL,EAAQJ,EAAGE,EAAQK,GAC1C3X,KAAK+W,WAAWa,OAAOzL,EAAIqL,EAAQJ,EAAGE,EAAQK,GAGlD3X,KAAK6W,OAAOe,OAAO5X,KAAKiF,MAAQmS,EAAGE,GACnCtX,KAAK6W,OAAOgB,OACZ7X,KAAK+W,WAAWa,OAAO5X,KAAKiF,MAAQmS,EAAGE,GACvCtX,KAAK+W,WAAWc,OAGhB7X,KAAK6W,OAAOiB,SAAS,EAAGR,EAAQF,EAAGpX,KAAKiF,MAAOmS,IAGnDtB,eAAgB,SAAUxT,GACtB,GAAIsT,GAAM1O,KAAKK,MACXvH,KAAKiF,MAAQ3C,GACbtC,KAAKD,OAAOf,UAChBgB,MAAK2T,MAAM3T,KAAKuW,cAAgBtR,MAAO2Q,EAAM,QAGjDzP,QAAS,SAAUxD,GACf,GAAI1B,GAAKjB,KACL+X,EAAS5X,SAASuB,cAAc,OACpCqW,GAAOrV,GAAKC,EAAKD,GACbC,EAAKmD,MAAsB,YAAdnD,EAAKmD,OAClBiS,EAAOC,UAAY,kBAEvBhY,KAAK0T,QAAQ1R,YAAY+V,EACzB,IAAI1L,EAEA1J,GAAKuI,YACLmB,EAAUlM,SAASuB,cAAc,WACjC2K,EAAQ3J,GAAKC,EAAKD,GAAK,WACvB2J,EAAQ2L,UAA0B,YAAdrV,EAAKmD,KACrB,+BAAiC,qBACrCiS,EAAO/V,YAAYqK,IAGvB0L,EAAO3W,iBAAiB,YAAa,SAAU6B,GAC3ChC,EAAGE,UAAU,YAAawB,EAAMM,KAEpC8U,EAAO3W,iBAAiB,aAAc,SAAU6B,GAC5ChC,EAAGE,UAAU,aAAcwB,EAAMM,KAErC8U,EAAO3W,iBAAiB,QAAS,SAAU6B,GACvChC,EAAGE,UAAU,aAAcwB,EAAMM,KAGrCN,EAAKuI,WAAc,WACf,GAAIrI,MAEAkS,EAAY,SAAU9R,GACtBA,EAAE+R,kBACFnS,EAAKuB,gBAAkBvB,EAAK8D,cAAgB,KAEhDxG,UAASiB,iBAAiB,UAAW2T,GACrC9T,EAAGI,GAAG,UAAW,WACblB,SAASmB,oBAAoB,UAAWyT,KAG5C1I,EAAQjL,iBAAiB,YAAa,SAAU6B,GAC5CA,EAAE+R,kBACFnS,EAAKuB,gBAAkBnD,EAAGiT,YAAYjR,KAG1ChC,EAAGyS,QAAQtS,iBAAiB,YAAalD,WAAW+B,KAAK4N,SAAS,SAAU5K,GACxEA,EAAE+R,kBAC0B,MAAxBnS,EAAKuB,kBACLvB,EAAK8D,cAAgB1F,EAAGiT,YAAYjR,GACpChC,EAAGE,UAAU,YAAa0B,EAAMF,KAErC,QAGP3C,KAAKiG,WAAWtD,GAEZA,EAAKuI,YACLlL,KAAK2T,MAAMtH,GACP1G,SAAU,WACVsS,OAAQ,aACRhT,MAAO,OACP7G,OAAQ,SAEZ4B,KAAK2T,MAAMtH,GACPkI,KAAMlI,EAAQ6L,YAAc,EAAI,GAAK,KACrCC,IAAKJ,EAAOK,aAAe,EAAI/L,EAAQ+L,aAAe,EAAI,KAC1DC,gBAAiB1V,EAAKqI,UAKlC/E,WAAY,SAAUtD,GAClB,GAAIoV,GAAS5X,SAASmY,eAAe3V,EAAKD,GAC1CqV,GAAOQ,MAAQ5V,EAAK0I,WACpBrL,KAAK2T,MAAMoE,GACP3Z,OAAQ,OACRuH,SAAU,WACV2Q,OAAQ,EACRrR,MAAOtC,EAAKsC,MAAQ,KACpBsP,KAAMrN,KAAKC,IAAI,EAAGD,KAAKK,MACnB5E,EAAK+C,WAAa1F,KAAKyU,YAAe9R,EAAKsC,MAAQ,IAClD,KACLoT,gBAAiB1V,EAAKqI,SAI9B9E,WAAY,SAAUvD,GAClB,GAAIoV,GAAS5X,SAASmY,eAAe3V,EAAKD,GACtCqV,IACA/X,KAAK0T,QAAQ3R,YAAYgW,IAIjC/Q,UAAW,SAAUR,GACjB,GAAIvF,GAAKjB,KACLwY,EAAWrY,SAASuB,cAAc,SACtC8W,GAAS9V,GAAK8D,EAAO9D,GACrB1C,KAAK0T,QAAQ1R,YAAYwW,GAEzBA,EAASpX,iBAAiB,YAAa,SAAU6B,GAC7ChC,EAAGE,UAAU,cAAeqF,EAAQvD,KAExCuV,EAASpX,iBAAiB,aAAc,SAAU6B,GAC9ChC,EAAGE,UAAU,eAAgBqF,EAAQvD,KAEzCuV,EAASpX,iBAAiB,QAAS,SAAU6B,GACzChC,EAAGE,UAAU,eAAgBqF,EAAQvD,KAGzCjD,KAAK8G,aAAaN,IAGtBM,aAAc,SAAUN,GACpB,GAAIgS,GAAWrY,SAASmY,eAAe9R,EAAO9D,IAC1C6R,EAAOrN,KAAKC,IAAI,EAAGD,KAAKK,MACxBf,EAAOpC,gBAAkBpE,KAAKyU,cAC9BxP,EAAQiC,KAAKC,IAAI,EAAGD,KAAKK,MACzBf,EAAOG,cAAgB3G,KAAKyU,cAAgBF,CAEhDvU,MAAK2T,MAAM6E,GACPpa,OAAQ,OACRuH,SAAU,WACV2Q,OAAQ,EACR/B,KAAMA,EAAO,KACb4D,IAAK,MACLlT,MAAOA,EAAQ,KACfoT,gBAAiB7R,EAAOwE,SAIhCjE,aAAc,SAAUP,GACpB,GAAIgS,GAAWrY,SAASmY,eAAe9R,EAAO9D,GAC1C8V,IACAxY,KAAK0T,QAAQ3R,YAAYyW,IAIjCzC,cAAe,WACX/V,KAAKkW,iBAELlW,KAAKgX,YAAYK,UAAYrX,KAAKD,OAAOvB,cACzC,IAAIia,GAAIzY,KAAKkS,aAAelS,KAAKiF,MAC7BA,EAAQjF,KAAKmS,WAAanS,KAAKiF,MAAQwT,CAE3CzY,MAAKgX,YAAYc,SAASW,EAAG,EAAGxT,EAAOjF,KAAK5B,SAGhD8X,eAAgB,WACZlW,KAAKgX,YAAYG,UAAU,EAAG,EAAGnX,KAAKiF,MAAOjF,KAAK5B,SAGtD+X,oBAAqB,SAAUH,EAAOC,GAClCjW,KAAKkG,WAAW8P,GAChBhW,KAAKkG,WAAW+P","sourceRoot":"/"}